oedisi/__init__.py
oedisi/componentframework/__init__.py
oedisi/componentframework/basic_component.py
oedisi/componentframework/mock_component.py
oedisi/componentframework/mock_component.sh
oedisi/componentframework/system_configuration.py
oedisi/componentframework/wiring_diagram_utils.py
oedisi/tools/__init__.py
oedisi/tools/api.py
oedisi/tools/broker_utils.py
oedisi/tools/cli_tools.py
oedisi/tools/metrics.py
oedisi/tools/pausing_broker.py
oedisi/tools/testing_broker.py
oedisi/types/__init__.py
oedisi/types/common.py
oedisi/types/data_types.py
oedisi/types/generate_schema.py
oedisi/types/schemas/AdmittanceMatrix.json
oedisi/types/schemas/AdmittanceSparse.json
oedisi/types/schemas/CapacitorStates.json
oedisi/types/schemas/Command.json
oedisi/types/schemas/CommandList.json
oedisi/types/schemas/CostArray.json
oedisi/types/schemas/CurrentsAngle.json
oedisi/types/schemas/CurrentsImaginary.json
oedisi/types/schemas/CurrentsMagnitude.json
oedisi/types/schemas/CurrentsReal.json
oedisi/types/schemas/Injection.json
oedisi/types/schemas/InverterControl.json
oedisi/types/schemas/InverterControlList.json
oedisi/types/schemas/MeasurementArray.json
oedisi/types/schemas/OperationalCosts.json
oedisi/types/schemas/PowersAngle.json
oedisi/types/schemas/PowersImaginary.json
oedisi/types/schemas/PowersMagnitude.json
oedisi/types/schemas/PowersReal.json
oedisi/types/schemas/ReactiveCostFunctions.json
oedisi/types/schemas/ReactiveWholesalePrices.json
oedisi/types/schemas/RealCostFunctions.json
oedisi/types/schemas/RealWholesalePrices.json
oedisi/types/schemas/RegulatorStates.json
oedisi/types/schemas/RootModel[List[Command]].json
oedisi/types/schemas/RootModel[List[InverterControl]].json
oedisi/types/schemas/SolarIrradiances.json
oedisi/types/schemas/StateArray.json
oedisi/types/schemas/StatesOfCharge.json
oedisi/types/schemas/SwitchStates.json
oedisi/types/schemas/Temperatures.json
oedisi/types/schemas/Topology.json
oedisi/types/schemas/VVControl.json
oedisi-3.0.1.dist-info/licenses/LICENSE.md
oedisi-3.0.1.dist-info/METADATA
oedisi-3.0.1.dist-info/WHEEL
oedisi-3.0.1.dist-info/entry_points.txt
oedisi-3.0.1.dist-info/top_level.txt
oedisi-3.0.1.dist-info/RECORD
