Metadata-Version: 2.4
Name: oedisi
Version: 3.0.1
Summary: Orchestration interface for HELICS power simulations
Author-email: Joseph McKinsey <joseph.mckinsey@nrel.gov>
License: BSD 3-Clause
Keywords: oedisi,gadal,helics
Classifier: Development Status :: 4 - Beta
Classifier: Intended Audience :: Science/Research
Classifier: License :: OSI Approved :: BSD License
Classifier: Natural Language :: English
Classifier: Programming Language :: Python :: 3.10
Classifier: Programming Language :: Python :: 3.11
Classifier: Programming Language :: Python :: 3.12
Classifier: Programming Language :: Python :: 3.13
Requires-Python: >=3.10
License-File: LICENSE.md
Requires-Dist: helics>=3.4
Requires-Dist: pydantic~=2.0
Requires-Dist: psutil
Requires-Dist: click
Requires-Dist: pyyaml~=6.0
Requires-Dist: kubernetes>=29.0
Provides-Extra: test
Requires-Dist: black; extra == "test"
Requires-Dist: bump-my-version; extra == "test"
Requires-Dist: mypy~=1.0; extra == "test"
Requires-Dist: pre-commit; extra == "test"
Requires-Dist: pytest; extra == "test"
Requires-Dist: pytest-cov; extra == "test"
Requires-Dist: ruff; extra == "test"
Requires-Dist: httpx; extra == "test"
Requires-Dist: fastapi~=0.104; extra == "test"
Requires-Dist: uvicorn; extra == "test"
Requires-Dist: numpy; extra == "test"
Requires-Dist: pandas; extra == "test"
Requires-Dist: pyarrow; extra == "test"
Provides-Extra: metrics
Requires-Dist: pandas; extra == "metrics"
Requires-Dist: numpy; extra == "metrics"
Requires-Dist: pyarrow; extra == "metrics"
Dynamic: license-file
